cartridge/__init__.py
cartridge/project_template/__init__.py
cartridge/project_template/manage.py
cartridge/project_template/project_name/__init__.py
cartridge/project_template/project_name/local_settings.py.template
cartridge/project_template/project_name/settings.py
cartridge/project_template/project_name/urls.py
cartridge/shop/__init__.py
cartridge/shop/admin.py
cartridge/shop/checkout.py
cartridge/shop/defaults.py
cartridge/shop/fields.py
cartridge/shop/forms.py
cartridge/shop/managers.py
cartridge/shop/middleware.py
cartridge/shop/models.py
cartridge/shop/page_processors.py
cartridge/shop/translation.py
cartridge/shop/urls.py
cartridge/shop/utils.py
cartridge/shop/views.py
cartridge/shop/fixtures/cartridge_optional.json
cartridge/shop/fixtures/cartridge_required.json
cartridge/shop/locale/ar/LC_MESSAGES/django.mo
cartridge/shop/locale/ar/LC_MESSAGES/django.po
cartridge/shop/locale/ca/django.mo
cartridge/shop/locale/ca/django.po
cartridge/shop/locale/ca/LC_MESSAGES/django.mo
cartridge/shop/locale/ca/LC_MESSAGES/django.po
cartridge/shop/locale/cs/LC_MESSAGES/django.mo
cartridge/shop/locale/cs/LC_MESSAGES/django.po
cartridge/shop/locale/de/LC_MESSAGES/django.mo
cartridge/shop/locale/de/LC_MESSAGES/django.po
cartridge/shop/locale/en/LC_MESSAGES/django.mo
cartridge/shop/locale/en/LC_MESSAGES/django.po
cartridge/shop/locale/es/LC_MESSAGES/django.mo
cartridge/shop/locale/es/LC_MESSAGES/django.po
cartridge/shop/locale/fa/LC_MESSAGES/django.mo
cartridge/shop/locale/fa/LC_MESSAGES/django.po
cartridge/shop/locale/fa_IR/LC_MESSAGES/django.mo
cartridge/shop/locale/fa_IR/LC_MESSAGES/django.po
cartridge/shop/locale/fi/LC_MESSAGES/django.mo
cartridge/shop/locale/fi/LC_MESSAGES/django.po
cartridge/shop/locale/fr/LC_MESSAGES/django.mo
cartridge/shop/locale/fr/LC_MESSAGES/django.po
cartridge/shop/locale/hr_HR/LC_MESSAGES/django.mo
cartridge/shop/locale/hr_HR/LC_MESSAGES/django.po
cartridge/shop/locale/it/LC_MESSAGES/django.mo
cartridge/shop/locale/it/LC_MESSAGES/django.po
Cartridge-1.3.4.dist-info/LICENSE
Cartridge-1.3.4.dist-info/METADATA
Cartridge-1.3.4.dist-info/WHEEL
Cartridge-1.3.4.dist-info/top_level.txt
Cartridge-1.3.4.dist-info/RECORD
