Metadata-Version: 2.1
Name: Cartridge
Version: 1.3.4
Summary: A Django shopping cart application.
Home-page: http://cartridge.jupo.org/
Author: Stephen McDonald
Author-email: stephen.mc@gmail.com
License: BSD
Classifier: Development Status :: 5 - Production/Stable
Classifier: Environment :: Web Environment
Classifier: Framework :: Django
Classifier: Intended Audience :: Developers
Classifier: License :: OSI Approved :: BSD License
Classifier: Operating System :: OS Independent
Classifier: Programming Language :: Python
Classifier: Programming Language :: Python :: 3
Classifier: Programming Language :: Python :: 3.7
Classifier: Programming Language :: Python :: 3.8
Classifier: Programming Language :: Python :: 3.9
Classifier: Programming Language :: Python :: 3.10
Classifier: Framework :: Django
Classifier: Framework :: Django :: 2.2
Classifier: Framework :: Django :: 3.2
Classifier: Framework :: Django :: 4.0
Classifier: Topic :: Internet :: WWW/HTTP
Classifier: Topic :: Internet :: WWW/HTTP :: Dynamic Content
Classifier: Topic :: Internet :: WWW/HTTP :: WSGI
Classifier: Topic :: Software Development :: Libraries :: Application Frameworks
Classifier: Topic :: Software Development :: Libraries :: Python Modules
Requires-Python: >=3.7
License-File: LICENSE
Requires-Dist: mezzanine (<7,>=6)
Requires-Dist: xhtml2pdf
Provides-Extra: codestyle
Requires-Dist: flake8 (<4,>=3) ; extra == 'codestyle'
Requires-Dist: black (==22.3.0) ; extra == 'codestyle'
Requires-Dist: isort (<6,>=5) ; extra == 'codestyle'
Requires-Dist: pyupgrade (<3,>=2) ; extra == 'codestyle'
Provides-Extra: stripe
Requires-Dist: stripe ; extra == 'stripe'
Provides-Extra: testing
Requires-Dist: pytest-django (<5,>=4) ; extra == 'testing'
Requires-Dist: pytest-cov (<3,>=2) ; extra == 'testing'
